kcfconvoy/Compound.py
kcfconvoy/KCFmat.py
kcfconvoy/KCFvec.py
kcfconvoy/Library.py
kcfconvoy/__init__.py
kcfconvoy/util.py
kcfconvoy-0.0.5.dist-info/LICENSE
kcfconvoy-0.0.5.dist-info/METADATA
kcfconvoy-0.0.5.dist-info/WHEEL
kcfconvoy-0.0.5.dist-info/top_level.txt
kcfconvoy-0.0.5.dist-info/RECORD
