Metadata-Version: 2.1
Name: kcfconvoy
Version: 0.0.5
Summary: KCF-Convoy: efficient Python package to convert KCF chemical substructure fingerprints
Home-page: https://github.com/KCF-Convoy/kcfconvoy
Author: maskot1977
Author-email: maskot@chemsys.t.u-tokyo.ac.jp
License: MIT
Keywords: bio-Informatics kcf kcfconvoy smiles
Platform: UNKNOWN
Classifier: Development Status :: 5 - Production/Stable
Classifier: License :: OSI Approved :: MIT License
Classifier: Operating System :: MacOS :: MacOS X
Classifier: Operating System :: POSIX :: Linux
Classifier: Programming Language :: Python
Classifier: Programming Language :: Python :: 3.4
Classifier: Programming Language :: Python :: 3.5
Classifier: Programming Language :: Python :: 3.6
Classifier: Programming Language :: Python :: 3.7
Classifier: Programming Language :: Python :: 3 :: Only
Classifier: Topic :: Scientific/Engineering
Classifier: Topic :: Scientific/Engineering :: Bio-Informatics
Classifier: Topic :: Scientific/Engineering :: Chemistry
Classifier: Topic :: Software Development :: Libraries :: Python Modules
Requires-Dist: IPython
Requires-Dist: matplotlib
Requires-Dist: networkx (==2.3)
Requires-Dist: numpy
Requires-Dist: pandas
Requires-Dist: sklearn
